[{"id": 46010357, "title": "Cloudfare: The Rust Community Knew This Was Coming", "cluster": 12, "x": 16.049739837646484, "y": 0.8468341827392578}, {"id": 45980129, "title": "How Cloudflare uses Rust to serve (and break) millions of websites", "cluster": 12, "x": 16.053119659423828, "y": 0.8447155952453613}, {"id": 45788478, "title": "Cloudflare just got faster and more secure, powered by Rust", "cluster": 12, "x": 16.053850173950195, "y": 0.8440267443656921}, {"id": 45530180, "title": "Cloudflare just got faster and more secure, powered by Rust", "cluster": 12, "x": 16.054262161254883, "y": 0.8433219790458679}, {"id": 45397345, "title": "Cloudflare just got faster and more secure, powered by Rust", "cluster": 12, "x": 16.054460525512695, "y": 0.8433324694633484}, {"id": 45386589, "title": "Cloudflare just got faster and more secure, powered by Rust", "cluster": 12, "x": 16.054651260375977, "y": 0.8426152467727661}, {"id": 44093649, "title": "The Agentic Web and Original Sin (Of Ads)", "cluster": 12, "x": 16.179590225219727, "y": 0.18024641275405884}, {"id": 44073241, "title": "The Agentic Web and Original Sin", "cluster": 12, "x": 16.18017578125, "y": 0.1790292114019394}, {"id": 44059003, "title": "The Agentic Web and Original Sin", "cluster": 12, "x": 16.18022346496582, "y": 0.17877408862113953}, {"id": 44051204, "title": "The Agentic Web and Original Sin", "cluster": 12, "x": 16.180465698242188, "y": 0.17822414636611938}, {"id": 44047761, "title": "The Agentic Web and Original Sin", "cluster": 12, "x": 16.18036651611328, "y": 0.17844244837760925}, {"id": 44042752, "title": "The Agentic Web and Original Sin", "cluster": 12, "x": 16.180816650390625, "y": 0.1778409630060196}, {"id": 44034987, "title": "Microsoft CTO Kevin Scott on the birth of the agentic web", "cluster": 12, "x": 16.181297302246094, "y": 0.17838917672634125}, {"id": 43186542, "title": "ExpressVPN gets faster and more secure, thanks to Rust", "cluster": 12, "x": 16.05628776550293, "y": 0.8410838842391968}]